import_completer/__init__.py
import_completer/code_scanner.py
import_completer/completion_engine.py
import_completer/config.py
import_completer/language_server.py
import_completer/path_discovery.py
import_completer/symbols_database.py
import_completer/types.py
import_completer-0.4.1.dist-info/METADATA
import_completer-0.4.1.dist-info/WHEEL
import_completer-0.4.1.dist-info/entry_points.txt
import_completer-0.4.1.dist-info/RECORD
