Metadata-Version: 2.4
Name: import-completer
Version: 0.4.1
Requires-Python: >=3.13
Requires-Dist: aiosqlite==0.21.0
Requires-Dist: click>=8.0.0
Requires-Dist: loguru==0.7.3
Requires-Dist: pygls==2.0.0
Requires-Dist: tree-sitter-python==0.23.6
Requires-Dist: tree-sitter==0.24.0
